LICENSE
MANIFEST.in
README.md
setup.py
cytocipher/__init__.py
cytocipher/ld.py
cytocipher/pl.py
cytocipher/tl.py
cytocipher.egg-info/PKG-INFO
cytocipher.egg-info/SOURCES.txt
cytocipher.egg-info/dependency_links.txt
cytocipher.egg-info/requires.txt
cytocipher.egg-info/top_level.txt
cytocipher/plotting/__init__.py
cytocipher/plotting/act_helpers.py
cytocipher/plotting/act_plots.py
cytocipher/plotting/bfs_plots.py
cytocipher/plotting/cd_helpers.py
cytocipher/plotting/cluster_diagnostics.py
cytocipher/plotting/general_plots.py
cytocipher/plotting/sankey.py
cytocipher/plotting/utils.py
cytocipher/score_and_merge/__init__.py
cytocipher/score_and_merge/_group_methods.py
cytocipher/score_and_merge/_neighbors.py
cytocipher/score_and_merge/cluster_merge.py
cytocipher/score_and_merge/cluster_score.py
cytocipher/score_and_merge/group_optimisation.py
cytocipher/utils/__init__.py
cytocipher/utils/general.py
cytocipher/utils/r_helpers.py
img/cytocipher_icon.png
img/enrichscore_violin_example.png
img/example_heatmap.png