Metadata-Version: 2.1
Name: cytocipher
Version: 0.1.20
Summary: Cluster significance analysis in scRNA-seq
Home-page: https://github.com/BradBalderson/Cytocipher
Author: Brad Balderson
Author-email: brad.balderson@uqconnect.edu.au
License: GNU GENERAL PUBLIC LICENSE V3
Classifier: Development Status :: 5 - Production/Stable
Classifier: Intended Audience :: Science/Research
Classifier: License :: OSI Approved :: GNU General Public License v3 (GPLv3)
Classifier: Operating System :: MacOS :: MacOS X
Classifier: Operating System :: POSIX :: Linux
Classifier: Programming Language :: Python :: 3.8
License-File: LICENSE
